users/__init__.py
users/admin.py
users/apps.py
users/models.py
users/serializers.py
users/tests.py
users/urls.py
users/utils.py
users/views.py
users/migrations/0001_initial.py
users/migrations/__init__.py
jevan_library-0.0.26.dist-info/LICENSE.md
jevan_library-0.0.26.dist-info/LICENSE.txt
jevan_library-0.0.26.dist-info/METADATA
jevan_library-0.0.26.dist-info/WHEEL
jevan_library-0.0.26.dist-info/top_level.txt
jevan_library-0.0.26.dist-info/RECORD
