Metadata-Version: 2.1
Name: jevan-library
Version: 0.0.26
Summary: Core library for each project developed by Jevan Solutions
Home-page: 
Author: Jevan Solutions
Author-email: jevan.xtrm@gmail.com
Classifier: Programming Language :: Python :: 3
Classifier: License :: OSI Approved :: MIT License
Classifier: Operating System :: OS Independent
Requires-Python: >=3.6
License-File: LICENSE.md
License-File: LICENSE.txt
